[{"i":13362,"t":"H & D Adventure Compilation","g":"Compilation","m":"ZX-Spectrum 48K","f":[{"l":"/pub/sinclair/compilations/h/HDAdventureCompilation.tzx.zip","y":"Tape image","s":59894},{"l":"/pub/sinclair/screens/in-game/h/HDAdventureCompilation.gif","y":"Running screen","s":6219}]},{"i":17707,"t":"H-Bloc","g":"Arcade Game: Action","m":"ZX-Spectrum 48K","f":[{"l":"/pub/sinclair/games/h/H-Bloc.tap.zip","y":"Tape image","s":1055},{"l":"/pub/sinclair/screens/in-game/h/H-Bloc.gif","y":"Running screen","s":1418},{"l":"/pub/sinclair/games-info/h/H-Bloc.pdf","y":"Instructions","s":407231},{"l":"/pub/sinclair/games-info/h/H-Bloc.txt","y":"Instructions","s":941}]},{"i":38917,"t":"H-Bomb Harry","g":"Arcade Game: Action","m":"ZX-Spectrum 48K","f":[{"l":"/zxdb/sinclair/entries/0038917/H-BombHarry.tap.zip","y":"Tape image","s":3942},{"l":"/zxdb/sinclair/entries/0038917/0038917-run-1.scr","y":"Running screen","s":6912}]},{"i":7453,"t":"H-Core","g":"Demoscene: Music","m":"ZX-Spectrum 128K","f":[{"l":"/pub/sinclair/demos/h/H-Core.tap.zip","y":"Tape image","s":10794},{"l":"/pub/sinclair/screens/load/h/scr/H-Core.scr","y":"Loading screen","s":6912},{"l":"/pub/sinclair/screens/in-game/h/H-Core.gif","y":"Running screen","s":3538}]},{"i":2235,"t":"H.A.R.D.","g":"Arcade Game: Shoot-em-up","m":"ZX-Spectrum 48K","f":[{"l":"/pub/sinclair/games/h/H.A.R.D..tzx.zip","y":"Tape image","s":7495},{"l":"/pub/sinclair/games/h/H.A.R.D..tap.zip","y":"Tape image","s":8172},{"l":"/pub/sinclair/screens/load/h/scr/H.A.R.D..scr","y":"Loading screen","s":6912},{"l":"/pub/sinclair/screens/in-game/h/H.A.R.D..gif","y":"Running screen","s":4208},{"l":"/pub/sinclair/games-maps/h/H.A.R.D..png","y":"Game map","s":22215},{"l":"https://archive.org/download/rzxarchive/hard.rzx","y":"RZX playback file","s":null}]},{"i":2247,"t":"H.A.T.E.","g":"Arcade Game: Shoot-em-up","m":"ZX-Spectrum 48K","f":[{"l":"/pub/sinclair/games/h/H.A.T.E..tzx.zip","y":"Tape image","s":44604},{"l":"/pub/sinclair/games/h/H.A.T.E..dsk.zip","y":"Disk image","s":35526},{"l":"/pub/sinclair/games/h/H.A.T.E..tap.zip","y":"Tape image","s":26625},{"l":"/pub/sinclair/games/h/H.A.T.E.(ErbeSoftwareS.A.).tzx.zip","y":"Tape image","s":18974},{"l":"/pub/sinclair/games/h/H.A.T.E.(ErbeSoftwareS.A.).tap.zip","y":"Tape image","s":18892},{"l":"/pub/sinclair/screens/load/h/scr/H.A.T.E..scr","y":"Loading screen","s":6912},{"l":"/pub/sinclair/screens/in-game/h/H.A.T.E..gif","y":"Running screen","s":4794},{"l":"/pub/sinclair/games-info/h/H.A.T.E.(ErbeSoftwareS.A.).txt","y":"Instructions","s":3270},{"l":"/pub/sinclair/games-maps/h/H.A.T.E..jpg","y":"Game map","s":374529},{"l":"/pub/sinclair/games-maps/h/H.A.T.E._2.png","y":"Game map","s":90263},{"l":"/pub/sinclair/games-inlays/Rereleases/h/H.A.T.E.(ErbeSoftwareS.A.).jpg","y":"Inlay - Front","s":69332},{"l":"/pub/sinclair/games-adverts/h/H.A.T.E..jpg","y":"Advertisement","s":277431},{"l":"/pub/sinclair/music/ay/games/h/H.A.T.E..ay.zip","y":"Ripped in-game/theme music in AY format","s":1767},{"l":"/zxdb/sinclair/pokes/h/H.A.T.E. (1989)(Gremlin Graphics Software).pok","y":"POK pokes file","s":33},{"l":"/zxdb/sinclair/entries/0002247/HATE(EN).txt","y":"Instructions","s":4670},{"l":"/zxdb/sinclair/entries/0002247/HATE.jpg","y":"Inlay - Front","s":1191352},{"l":"https://archive.org/download/rzxarchive/hate.rzx","y":"RZX playback file","s":null},{"l":"/zxdb/sinclair/entries/0002247/HATE(Fixed).dsk.zip","y":"Disk image","s":35518},{"l":"/zxdb/sinclair/entries/0002247/HATE(MULTI-LANG).pdf","y":"Instructions","s":546879},{"l":"/zxdb/sinclair/entries/0002247/HATE_Media.jpg","y":"Media scan","s":92222}]},{"i":2301,"t":"H.E.R.O.","g":"Arcade Game: Maze","m":"ZX-Spectrum 48K","f":[{"l":"/pub/sinclair/screens/load/h/scr/H.E.R.O..scr","y":"Loading screen","s":6912},{"l":"/pub/sinclair/screens/in-game/h/H.E.R.O..gif","y":"Running screen","s":1671},{"l":"/pub/sinclair/games-maps/h/H.E.R.O..png","y":"Game map","s":218243},{"l":"/pub/sinclair/games-adverts/h/H.E.R.O..jpg","y":"Advertisement","s":162841},{"l":"/zxdb/sinclair/pokes/h/H.E.R.O. (1984)(Activision Inc).pok","y":"POK pokes file","s":166},{"l":"/zxdb/sinclair/entries/0002301/HERO(FirebirdSoftware).jpg","y":"Inlay - Front","s":368609},{"l":"/zxdb/sinclair/entries/0002301/HERO.jpg","y":"Inlay - Front","s":314689},{"l":"/zxdb/sinclair/entries/0002301/HERO(FirebirdSoftware)_Back.jpg","y":"Inlay - Back","s":281453},{"l":"/zxdb/sinclair/entries/0002301/HERO.tzx.zip","y":"Tape image","s":15658},{"l":"/zxdb/sinclair/entries/0002301/HERO(EN).txt","y":"Instructions","s":7246},{"l":"/zxdb/sinclair/entries/0002301/HERO.rzx.zip","y":"RZX playback file","s":275919},{"l":"/zxdb/sinclair/entries/0002301/HERO(EN).pdf","y":"Instructions","s":465068},{"l":"/zxdb/sinclair/entries/0002301/HERO(ProeinSoftLine).tzx.zip","y":"Tape image","s":15674},{"l":"/zxdb/sinclair/entries/0002301/HERO(ProeinSoftLine)_Front.jpg","y":"Inlay - Front","s":657014},{"l":"/zxdb/sinclair/entries/0002301/HERO(ProeinSoftLine)_SideA.jpg","y":"Media scan","s":27387},{"l":"/zxdb/sinclair/entries/0002301/HERO(ProeinSoftLine)_SideB.jpg","y":"Media scan","s":26306},{"l":"/zxdb/sinclair/entries/0002301/HERO(FirebirdSoftware)_Media.jpg","y":"Media scan","s":131658},{"l":"/zxdb/sinclair/entries/0002301/HERO_SideA.jpg","y":"Media scan","s":89375},{"l":"/zxdb/sinclair/entries/0002301/HERO_SideB.jpg","y":"Media scan","s":85545}]},{"i":36387,"t":"H.E.R.O. Returns","g":"Arcade Game: Action","m":"ZX-Spectrum 48K","f":[{"l":"/zxdb/sinclair/entries/0036387/HERO(WithIntro).tap.zip","y":"Tape image","s":29746},{"l":"/zxdb/sinclair/entries/0036387/HERO.tap.zip","y":"Tape image","s":16891},{"l":"/zxdb/sinclair/entries/0036387/HERO.txt","y":"Instructions","s":3342},{"l":"/zxdb/sinclair/entries/0036387/0036387-load-1.scr","y":"Loading screen","s":6912},{"l":"/zxdb/sinclair/entries/0036387/0036387-run-1.scr","y":"Running screen","s":6912},{"l":"/zxdb/sinclair/entries/0036387/HEROReturns(MatraComputerAutomations)_Back.jpg","y":"Inlay - Back","s":242504},{"l":"/zxdb/sinclair/entries/0036387/HEROReturns(MatraComputerAutomations)_Front.jpg","y":"Inlay - Front","s":155760},{"l":"/zxdb/sinclair/entries/0036387/HEROReturns(MatraComputerAutomations)_SideA.jpg","y":"Media scan","s":79875},{"l":"/zxdb/sinclair/entries/0036387/HEROReturns(MatraComputerAutomations)_SideB.jpg","y":"Media scan","s":77607},{"l":"https://archive.org/download/rzxarchive/heroreturns.rzx","y":"RZX playback file","s":null}]},{"i":6454,"t":"H.R.H.","g":"Adventure Game: Text/Illustrated","m":"ZX-Spectrum 48K","f":[{"l":"/pub/sinclair/games/h/H.R.H..tzx.zip","y":"Tape image","s":35085},{"l":"/pub/sinclair/games/h/H.R.H.V1.z80.zip","y":"Snapshot image","s":29171},{"l":"/pub/sinclair/games/h/H.R.H.V2.z80.zip","y":"Snapshot image","s":26664},{"l":"/pub/sinclair/games/h/H.R.H.(G.I.Games).tzx.zip","y":"Tape image","s":29146},{"l":"/pub/sinclair/games/h/H.R.H.(ZenobiSoftware).mgt.zip","y":"Disk image","s":32011},{"l":"/pub/sinclair/screens/load/h/scr/H.R.H..scr","y":"Loading screen","s":6912},{"l":"/pub/sinclair/screens/in-game/h/H.R.H..gif","y":"Running screen","s":2628},{"l":"/pub/sinclair/games-inlays/h/H.R.H..jpg","y":"Inlay - Front","s":83690},{"l":"https://archive.org/download/rzxarchive/hrh.rzx","y":"RZX playback file","s":null}]},{"i":13908,"t":"H.R.H. + Cuddles","g":"Compilation","m":"ZX-Spectrum 48K","f":[{"l":"/pub/sinclair/compilations/h/H.R.H.+Cuddles.tzx.zip","y":"Tape image","s":66910},{"l":"/pub/sinclair/screens/in-game/h/H.R.H.+Cuddles.gif","y":"Running screen","s":4421},{"l":"/pub/sinclair/games-inlays/Compilations/h/H.R.H.+Cuddles.jpg","y":"Inlay - Front","s":37815}]},{"i":2398,"t":"H.U.R.G.","g":"Utility: Game Creator","m":"ZX-Spectrum 48K","f":[{"l":"/pub/sinclair/utils/h/H.U.R.G..tzx.zip","y":"Tape image","s":25111},{"l":"/pub/sinclair/utils/h/H.U.R.G..tap.zip","y":"Tape image","s":24521},{"l":"/pub/sinclair/utils/h/H.U.R.G.(InvestronicaS.A.).tzx.zip","y":"Tape image","s":24052},{"l":"/pub/sinclair/utils/h/H.U.R.G.(DisenadorDeJuegosII)(Microbyte1).tzx.zip","y":"Tape image","s":17927},{"l":"/pub/sinclair/screens/load/h/scr/H.U.R.G..scr","y":"Loading screen","s":6912},{"l":"/pub/sinclair/screens/in-game/h/H.U.R.G..gif","y":"Running screen","s":3337},{"l":"/pub/sinclair/games-info/h/H.U.R.G..txt","y":"Instructions","s":55979},{"l":"/pub/sinclair/games-info/h/H.U.R.G.(DisenadorDeJuegosII)(InvestronicaS.A.).pdf","y":"Instructions","s":10616},{"l":"/pub/sinclair/games-info/h/H.U.R.G.(DisenadorDeJuegosII)(InvestronicaS.A.).txt","y":"Instructions","s":970},{"l":"/pub/sinclair/games-inlays/Rereleases/h/H.U.R.G.(DisenadorDeJuegosII)(InvestronicaS.A.).jpg","y":"Inlay - Front","s":88419},{"l":"/pub/sinclair/games-inlays/Rereleases/h/H.U.R.G.(DisenadorDeJuegosII)(Microbyte).jpg","y":"Inlay - Front","s":67034},{"l":"/pub/sinclair/games-adverts/h/H.U.R.G..jpg","y":"Advertisement","s":580082},{"l":"/pub/sinclair/games-adverts/h/H.U.R.G._2.jpg","y":"Advertisement","s":571418},{"l":"/zxdb/sinclair/entries/0002398/HURG.jpg","y":"Inlay - Front","s":255056},{"l":"/zxdb/sinclair/entries/0002398/HURG(EN).pdf","y":"Instructions","s":3964399},{"l":"/zxdb/sinclair/entries/0002398/HURG_SideA.jpg","y":"Media scan","s":88143},{"l":"/zxdb/sinclair/entries/0002398/HURG_SideB.jpg","y":"Media scan","s":90253}]},{"i":36064,"t":"H7N9","g":"Arcade Game: Maze","m":"ZX-Spectrum 48K","f":[{"l":"/zxdb/sinclair/entries/0036064/H7N9.tap.zip","y":"Tape image","s":9918},{"l":"/zxdb/sinclair/entries/0036064/H7N9.txt","y":"Instructions","s":164},{"l":"/zxdb/sinclair/entries/0036064/H7N9_SourceCode.zip","y":"Source code","s":11231},{"l":"/zxdb/sinclair/entries/0036064/0036064-run-1.png","y":"Running screen","s":97858}]},{"i":8232,"t":"HACK","g":"Utility: Hacker/Security","m":"ZX-Spectrum 48K","f":[{"l":"/pub/sinclair/utils/h/HACK.tzx.zip","y":"Tape image","s":2274},{"l":"/pub/sinclair/screens/in-game/h/HACK.gif","y":"Running screen","s":2876}]},{"i":28159,"t":"HAM 8x1","g":"Utility: Visual/Screen","m":"ZX-Spectrum 48K","f":[{"l":"/pub/sinclair/utils/h/HAM8x1.tap.zip","y":"Tape image","s":7664},{"l":"/pub/sinclair/games-extras/HAM8x1_SourceCode.zip","y":"Source code","s":16293},{"l":"/zxdb/sinclair/entries/0028159/0028159-run-1.png","y":"Running screen","s":19470}]},{"i":27262,"t":"HAM256 Viewer","g":"Utility: Visual/Screen","m":"ZX-Spectrum 48K","f":[{"l":"/pub/sinclair/utils/h/HAM256ViewerV0.3.tap.zip","y":"Tape image","s":7290},{"l":"/pub/sinclair/screens/in-game/h/HAM256Viewer.png","y":"Running screen","s":17636},{"l":"/pub/sinclair/games-info/h/HAM256Viewer.txt","y":"Instructions","s":1224},{"l":"/pub/sinclair/games-extras/HAM256Viewer_SourceCode.zip","y":"Source code","s":25882}]},{"i":36497,"t":"HELL YEAH!","g":"Arcade Game: Action","m":"ZX-Spectrum 48K","f":[{"l":"/zxdb/sinclair/entries/0036497/HELLYEAH!.txt","y":"Instructions","s":2787},{"l":"/zxdb/sinclair/entries/0036497/HELLYEAH!.tzx.zip","y":"Tape image","s":22674},{"l":"/zxdb/sinclair/entries/0036497/0036497-run-1.scr","y":"Running screen","s":6912},{"l":"/zxdb/sinclair/entries/0036497/HELLYEAH!.tap.zip","y":"Tape image","s":22637},{"l":"https://archive.org/download/rzxarchive/hellyeah.zip","y":"RZX playback file","s":null}]},{"i":36115,"t":"HEX Loader","g":"Programming: Assembler/Mcode","m":"ZX-Spectrum 48K","f":[{"l":"/zxdb/sinclair/entries/0036115/HEXLoader.tzx.zip","y":"Tape image","s":569},{"l":"/zxdb/sinclair/entries/0036115/0036115-run-1.scr","y":"Running screen","s":6912}]},{"i":11781,"t":"HI-T Spectrum Screen Enhancer","g":"Utility: Fonts/UDGs","m":"ZX-Spectrum 48K","f":[{"l":"/pub/sinclair/utils/h/HI-TSpectrumScreenEnhancerV1.3.tzx.zip","y":"Tape image","s":2675},{"l":"/pub/sinclair/screens/in-game/h/HI-TSpectrumScreenEnhancer.gif","y":"Running screen","s":2173}]},{"i":8261,"t":"HL ZX FORTH","g":"Programming: General","m":"ZX-Spectrum 16K/48K","f":[{"l":"/pub/sinclair/utils/h/HLZXFORTH.tap.zip","y":"Tape image","s":4663},{"l":"/pub/sinclair/screens/load/h/scr/HLZXForth.scr","y":"Loading screen","s":6912},{"l":"/pub/sinclair/screens/in-game/h/HLZXForth.gif","y":"Running screen","s":2877},{"l":"/pub/sinclair/games-info/h/HLZXForth_Spanish.pdf","y":"Scanned instructions","s":12826669}]},{"i":42273,"t":"HOL-ROCK SMEG-THESISER","g":"Utility: Music","m":"ZX-Spectrum 48K","f":[{"l":"/zxdb/sinclair/entries/0042273/HOL-ROCKSMEG-THESISER.tap.zip","y":"Tape image","s":4917},{"l":"/zxdb/sinclair/entries/0042273/HOL-ROCKSMEG-THESISER(EN).txt","y":"Instructions","s":14680},{"l":"/zxdb/sinclair/entries/0042273/HOL-ROCKSMEG-THESISER(EN)(LOG).txt","y":"Instructions","s":3966},{"l":"/zxdb/sinclair/entries/0042273/HOL-ROCKSMEG-THESISER-LOAD-1.scr","y":"Loading screen","s":6912},{"l":"/zxdb/sinclair/entries/0042273/HOL-ROCKSMEG-THESISER-RUN-1.scr","y":"Running screen","s":6912},{"l":"/zxdb/sinclair/entries/0042273/HOL-ROCKSMEG-THESISER_SourceCode.zip","y":"Source code","s":8452}]},{"i":22416,"t":"HOT-K","g":"Arcade Game: Action","m":"ZX-Spectrum 48K","f":[{"l":"/pub/sinclair/games/h/HOT-K.tzx.zip","y":"Tape image","s":10809},{"l":"/pub/sinclair/screens/in-game/h/HOT-K.gif","y":"Running screen","s":3587},{"l":"/pub/sinclair/games-info/h/HOT-K.txt","y":"Instructions","s":1867}]},{"i":36758,"t":"HS' Plotter","g":"Utility: Graphics","m":"ZX-Spectrum 48K","f":[{"l":"/zxdb/sinclair/entries/0036758/HSPlotter.tzx.zip","y":"Tape image","s":13055},{"l":"/zxdb/sinclair/entries/0036758/HSPlotter_Front.jpg","y":"Inlay - Front","s":339865},{"l":"/zxdb/sinclair/entries/0036758/0036758-load-1.scr","y":"Loading screen","s":6912},{"l":"/zxdb/sinclair/entries/0036758/0036758-run-1.scr","y":"Running screen","s":6912}]},{"i":15564,"t":"HS-Compiler","g":"Programming: General","m":"ZX-Spectrum 48K","f":[{"l":"/pub/sinclair/utils/h/HS-CompilerV1.1.tzx.zip","y":"Tape image","s":4894},{"l":"/pub/sinclair/screens/in-game/h/HS-Compiler.gif","y":"Running screen","s":1078},{"l":"/zxdb/sinclair/entries/0015564/HS-Compiler(Aackosoft).jpg","y":"Inlay - Front","s":963477},{"l":"/zxdb/sinclair/entries/0015564/HS-Compiler(Aackosoft)(NL).pdf","y":"Instructions","s":276955}]},{"i":38711,"t":"HYPERZAX","g":"Arcade Game: Shoot-em-up","m":"ZX-Spectrum 48K","f":[{"l":"/zxdb/sinclair/entries/0038711/HYPERZAX.tap.zip","y":"Tape image","s":14115},{"l":"/zxdb/sinclair/entries/0038711/0038711-open-1.scr","y":"Opening screen","s":6912},{"l":"/zxdb/sinclair/entries/0038711/0038711-run-1.scr","y":"Running screen","s":6912}]},{"i":36877,"t":"HaHa Writer","g":"Utility: Print","m":"ZX-Spectrum 48K","f":[{"l":"/zxdb/sinclair/entries/0036877/HaHaWriter.tap.zip","y":"Tape image","s":86589},{"l":"/zxdb/sinclair/entries/0036877/HaHaWriter_Front.jpg","y":"Inlay - Front","s":254059},{"l":"/zxdb/sinclair/entries/0036877/0036877-open-1.scr","y":"Opening screen","s":6912},{"l":"/zxdb/sinclair/entries/0036877/0036877-run-1.scr","y":"Running screen","s":6912}]},{"i":2199,"t":"Habilit","g":"Arcade Game: Maze","m":"ZX-Spectrum 48K","f":[{"l":"/pub/sinclair/games/h/Habilit.tzx.zip","y":"Tape image","s":8540},{"l":"/pub/sinclair/games/h/Habilit(BUGFIX).tzx.zip","y":"BUGFIX tape image","s":8557},{"l":"/pub/sinclair/games/h/Habilit.tap.zip","y":"Tape image","s":8389},{"l":"/pub/sinclair/screens/load/h/scr/Habilit.scr","y":"Loading screen","s":6912},{"l":"/pub/sinclair/screens/in-game/h/Habilit.gif","y":"Running screen","s":4097},{"l":"/pub/sinclair/games-info/h/Habilit.pdf","y":"Instructions","s":13355},{"l":"/pub/sinclair/games-inlays/h/Habilit.jpg","y":"Inlay - Front","s":74084},{"l":"/zxdb/sinclair/pokes/h/Habilit (1988)(Iber Software).pok","y":"POK pokes file","s":57}]},{"i":42249,"t":"Habitación 310: El Despertar","g":"Adventure Game: Text-Only","m":"ZX-Spectrum 48K","f":[{"l":"/zxdb/sinclair/entries/0042249/Habitacion310-ElDespertar.tap.zip","y":"Tape image","s":26210},{"l":"/zxdb/sinclair/entries/0042249/Habitacion310-ElDespertar-OPEN-1.scr","y":"Opening screen","s":6912},{"l":"/zxdb/sinclair/entries/0042249/Habitacion310-ElDespertar-RUN-1.scr","y":"Running screen","s":6912}]},{"i":38598,"t":"Hacia Mi Mundo","g":"Adventure Game: Text/Illustrated","m":"ZX-Spectrum 128K","f":[{"l":"/zxdb/sinclair/entries/0038598/0038598-open-1.scr","y":"Opening screen","s":6912},{"l":"/zxdb/sinclair/entries/0038598/0038598-run-1.scr","y":"Running screen","s":6912},{"l":"/zxdb/sinclair/entries/0038598/HaciaMiMundo.tzx.zip","y":"Tape image","s":47600}]},{"i":9227,"t":"Hack Attack","g":"Utility: Hacker/Security","m":"ZX-Spectrum 48K/128K","f":[{"l":"/pub/sinclair/utils/h/HackAttack.tzx.zip","y":"Tape image","s":11786},{"l":"/pub/sinclair/utils/h/HackAttack(HackAttack84).tzx.zip","y":"Tape image","s":10257},{"l":"/pub/sinclair/screens/load/h/scr/HackAttack.scr","y":"Loading screen","s":6912},{"l":"/pub/sinclair/screens/in-game/h/HackAttack.gif","y":"Running screen","s":4159},{"l":"/pub/sinclair/games-info/h/HackAttack.txt","y":"Instructions","s":1483}]},{"i":13831,"t":"Hack Attack 2","g":"Utility: Hacker/Security","m":"ZX-Spectrum 48K/128K","f":[{"l":"/pub/sinclair/utils/h/HackAttack2.tap.zip","y":"Tape image","s":22405},{"l":"/pub/sinclair/screens/load/h/scr/HackAttack2.scr","y":"Loading screen","s":6912},{"l":"/pub/sinclair/screens/in-game/h/HackAttack2.gif","y":"Running screen","s":3391},{"l":"/pub/sinclair/games-info/h/HackAttack2.txt","y":"Instructions","s":879}]},{"i":15560,"t":"Hack Pack","g":"Utility: Hacker/Security","m":"ZX-Spectrum 48K","f":[{"l":"/pub/sinclair/utils/h/HackPack.tzx.zip","y":"Tape image","s":32789},{"l":"/pub/sinclair/screens/load/h/scr/HackPack.scr","y":"Loading screen","s":6912},{"l":"/pub/sinclair/screens/in-game/h/HackPack.gif","y":"Running screen","s":1383}]},{"i":2200,"t":"Hacker","g":"Adventure Game: Graphic","m":"ZX-Spectrum 48K/128K","f":[{"l":"/pub/sinclair/screens/in-game/h/Hacker.gif","y":"Running screen","s":7026},{"l":"/pub/sinclair/games-info/h/Hacker.txt","y":"Instructions","s":633},{"l":"/pub/sinclair/games-maps/h/Hacker.gif","y":"Game map","s":7269},{"l":"/pub/sinclair/games-inlays/Rereleases/h/Hacker(ProeinSoftLine).jpg","y":"Inlay - Front","s":109428},{"l":"/pub/sinclair/games-adverts/h/Hacker.jpg","y":"Advertisement","s":125418},{"l":"/zxdb/sinclair/pokes/h/Hacker (1985)(Activision Inc).pok","y":"POK pokes file","s":370},{"l":"/zxdb/sinclair/entries/0002200/Hacker(Ricochet).jpg","y":"Inlay - Front","s":553685},{"l":"/zxdb/sinclair/entries/0002200/Hacker.jpg","y":"Inlay - Front","s":344847},{"l":"/zxdb/sinclair/entries/0002200/Hacker128K.jpg","y":"Inlay - Front","s":540020},{"l":"/zxdb/sinclair/entries/0002200/Hacker128K_Back.jpg","y":"Inlay - Back","s":260799},{"l":"/zxdb/sinclair/entries/0002200/Hacker(Ricochet).tzx.zip","y":"Tape image","s":22192},{"l":"/zxdb/sinclair/entries/0002200/Hacker.tzx.zip","y":"Tape image","s":23758},{"l":"/zxdb/sinclair/entries/0002200/Hacker(Ricochet)_Back.jpg","y":"Inlay - Back","s":151431},{"l":"/zxdb/sinclair/entries/0002200/Hacker.rzx.zip","y":"RZX playback file","s":137006},{"l":"/zxdb/sinclair/entries/0002200/Hacker_SideA.jpg","y":"Media scan","s":94943},{"l":"/zxdb/sinclair/entries/0002200/Hacker_SideA_2.jpg","y":"Media scan","s":131791},{"l":"/zxdb/sinclair/entries/0002200/Hacker_SideB.jpg","y":"Media scan","s":97831},{"l":"/zxdb/sinclair/entries/0002200/Hacker_SideB_2.jpg","y":"Media scan","s":137505},{"l":"/zxdb/sinclair/entries/0002200/Hacker(Ricochet)_Media.jpg","y":"Media scan","s":73270}]},{"i":2202,"t":"Hacker II: The Doomsday Papers","g":"Adventure Game: Graphic","m":"ZX-Spectrum 48K","f":[{"l":"/pub/sinclair/screens/load/h/scr/HackerII-TheDoomsdayPapers.scr","y":"Loading screen","s":6912},{"l":"/pub/sinclair/screens/in-game/h/HackerII-TheDoomsdayPapers.gif","y":"Running screen","s":3707},{"l":"/pub/sinclair/games-info/h/HackerII-TheDoomsdayPapers.txt","y":"Instructions","s":3297},{"l":"/pub/sinclair/games-maps/h/HackerII-TheDoomsdayPapers.jpg","y":"Game map","s":112909},{"l":"/pub/sinclair/games-maps/h/HackerII-TheDoomsdayPapers_2.jpg","y":"Game map","s":53411},{"l":"/pub/sinclair/games-maps/h/HackerII-TheDoomsdayPapers_3.jpg","y":"Game map","s":30749},{"l":"/pub/sinclair/games-adverts/h/HackerII-TheDoomsdayPapers.jpg","y":"Advertisement","s":206173},{"l":"/zxdb/sinclair/pokes/h/Hacker II The Doomsday Papers (1987)(Activision Inc).pok","y":"POK pokes file","s":197},{"l":"/zxdb/sinclair/entries/0002202/HackerII-TheDoomsdayPapers(Mastertronic).jpg","y":"Inlay - Front","s":361370},{"l":"/zxdb/sinclair/entries/0002202/HackerII-TheDoomsdayPapers.jpg","y":"Inlay - Front","s":448937},{"l":"/zxdb/sinclair/entries/0002202/HackerII-TheDoomsdayPapers(MastertronicLtd).tzx.zip","y":"Tape image","s":20506},{"l":"/zxdb/sinclair/entries/0002202/HackerII-TheDoomsdayPapers.tzx.zip","y":"Tape image","s":20713},{"l":"/zxdb/sinclair/entries/0002202/HackerII-TheDoomsdayPapers(Mastertronic)_Back.jpg","y":"Inlay - Back","s":219302},{"l":"/zxdb/sinclair/entries/0002202/HackerII-TheDoomsdayPapers(EN).pdf","y":"Instructions","s":1557404},{"l":"/zxdb/sinclair/entries/0002202/HackerII-TheDoomsdayPapers(MastertronicLtd)(MULTI-LANG).pdf","y":"Instructions","s":215959},{"l":"/zxdb/sinclair/entries/0002202/HackerII-TheDoomsdayPapers_SideA.jpg","y":"Media scan","s":123586},{"l":"/zxdb/sinclair/entries/0002202/HackerII-TheDoomsdayPapers_SideB.jpg","y":"Media scan","s":58610},{"l":"/zxdb/sinclair/entries/0002202/HackerII-TheDoomsdayPapers(Mastertronic)_Media.jpg","y":"Media scan","s":88146}]},{"i":15638,"t":"Hacking Utilities","g":"Utility: Hacker/Security","m":"ZX-Spectrum 48K","f":[{"l":"/pub/sinclair/utils/h/HackingUtilities.tzx.zip","y":"Tape image","s":10045},{"l":"/pub/sinclair/screens/in-game/h/HackingUtilities.gif","y":"Running screen","s":1671}]},{"i":43151,"t":"Hacking the Logon","g":"Adventure Game: Text-Only","m":"ZX-Spectrum 16K","f":[{"l":"/zxdb/sinclair/entries/0043151/HackingTheLogon.z80.zip","y":"Snapshot image","s":2618},{"l":"/zxdb/sinclair/entries/0043151/HackingTheLogon(EN).txt","y":"Instructions","s":984}]},{"i":9229,"t":"Hacks Amazing!","g":"Utility: Hacker/Security","m":"ZX-Spectrum 48K","f":[{"l":"/pub/sinclair/utils/h/HacksAmazing.tzx.zip","y":"Tape image","s":15453},{"l":"/pub/sinclair/screens/load/h/scr/HacksAmazing.scr","y":"Loading screen","s":6912},{"l":"/pub/sinclair/screens/in-game/h/HacksAmazing.gif","y":"Running screen","s":3547}]},{"i":31478,"t":"Hackup","g":"Utility: undetermined","m":"ZX-Spectrum 48K","f":[{"l":"/zxdb/sinclair/entries/0031478/Hackup.tzx.zip","y":"Tape image","s":1656},{"l":"/zxdb/sinclair/entries/0031478/0031478-run-1.scr","y":"Running screen","s":6912}]},{"i":10824,"t":"Hades","g":"Adventure Game: Text-Only","m":"ZX-Spectrum 48K","f":[{"l":"/pub/sinclair/games/h/Hades.tzx.zip","y":"Tape image","s":22527},{"l":"/pub/sinclair/screens/load/h/scr/Hades.scr","y":"Loading screen","s":6912},{"l":"/pub/sinclair/screens/in-game/h/Hades.gif","y":"Running screen","s":1365},{"l":"https://archive.org/download/rzxarchive/hades.rzx","y":"RZX playback file","s":null},{"l":"/zxdb/sinclair/entries/0010824/Hades_Front.jpg","y":"Inlay - Front","s":333590},{"l":"/zxdb/sinclair/entries/0010824/Hades_SideA.jpg","y":"Media scan","s":147951},{"l":"/zxdb/sinclair/entries/0010824/Hades_SideB.jpg","y":"Media scan","s":141817}]},{"i":15720,"t":"Hades","g":"Adventure Game: Text/Illustrated","m":"ZX-Spectrum 128K","f":[{"l":"/pub/sinclair/screens/in-game/h/Hades_2.gif","y":"Running screen","s":3178},{"l":"/zxdb/sinclair/entries/0015720/Hades.z80.zip","y":"Snapshot image","s":29453},{"l":"/zxdb/sinclair/entries/0015720/0015720-load-1.scr","y":"Loading screen","s":6912},{"l":"/zxdb/sinclair/entries/0015720/Hades.tzx.zip","y":"Tape image","s":48099}]},{"i":2204,"t":"Hades Nebula","g":"Arcade Game: Shoot-em-up","m":"ZX-Spectrum 48K","f":[{"l":"/pub/sinclair/games/h/HadesNebula.tzx.zip","y":"Tape image","s":25235},{"l":"/pub/sinclair/games/h/HadesNebula(BUGFIX).tzx.zip","y":"BUGFIX tape image","s":25164},{"l":"/pub/sinclair/games/h/HadesNebula.tap.zip","y":"Tape image","s":25120},{"l":"/pub/sinclair/games/h/HadesNebula(Gamebusters).tzx.zip","y":"Tape image","s":24378},{"l":"/pub/sinclair/games/h/HadesNebula(Gamebusters).tap.zip","y":"Tape image","s":24277},{"l":"/pub/sinclair/games/h/HadesNebula(MCMSoftwareS.A.).tzx.zip","y":"Tape image","s":24467},{"l":"/pub/sinclair/screens/load/h/scr/HadesNebula.scr","y":"Loading screen","s":6912},{"l":"/pub/sinclair/screens/in-game/h/HadesNebula.gif","y":"Running screen","s":4060},{"l":"/pub/sinclair/games-info/h/HadesNebula.txt","y":"Instructions","s":3911},{"l":"/pub/sinclair/games-info/h/HadesNebula(MCMSoftwareS.A.).pdf","y":"Instructions","s":9842},{"l":"/pub/sinclair/games-maps/h/HadesNebula.png","y":"Game map","s":317461},{"l":"/pub/sinclair/games-inlays/Rereleases/h/HadesNebula(MCMSoftwareS.A.).jpg","y":"Inlay - Front","s":47138},{"l":"/pub/sinclair/games-adverts/h/HadesNebula.jpg","y":"Advertisement","s":242217},{"l":"/pub/sinclair/music/ay/games/h/HadesNebula.ay.zip","y":"Ripped in-game/theme music in AY format","s":3064},{"l":"/pub/sinclair/music/mp3/HadesNebula.mp3.zip","y":"Sampled in-game/theme music in MP3 format","s":2098485},{"l":"/zxdb/sinclair/pokes/h/Hades Nebula (1987)(Nexus Productions).pok","y":"POK pokes file","s":78},{"l":"/zxdb/sinclair/entries/0002204/HadesNebula.jpg","y":"Inlay - Front","s":503177},{"l":"/zxdb/sinclair/entries/0002204/HadesNebula_Back.jpg","y":"Inlay - Back","s":337224},{"l":"https://archive.org/download/rzxarchive/hadesnebula.rzx","y":"RZX playback file","s":null},{"l":"/zxdb/sinclair/entries/0002204/HadesNebula(Gamebusters)_Back.jpg","y":"Inlay - Back","s":394471},{"l":"/zxdb/sinclair/entries/0002204/HadesNebula(Gamebusters)_Front.jpg","y":"Inlay - Front","s":395874},{"l":"/zxdb/sinclair/entries/0002204/HadesNebula(Gamebusters)_Media.jpg","y":"Media scan","s":83414},{"l":"/zxdb/sinclair/entries/0002204/HadesNebula_Media.jpg","y":"Media scan","s":124119}]},{"i":8234,"t":"Hado Basic","g":"Utility: undetermined","m":"ZX-Spectrum 48K","f":[{"l":"/pub/sinclair/utils/h/HadoBasic.z80.zip","y":"Snapshot image","s":2527},{"l":"/pub/sinclair/screens/in-game/h/HadoBasic.gif","y":"Running screen","s":2318}]},{"i":25528,"t":"Hadrian's Wall","g":"General: Education","m":"ZX-Spectrum 48K","f":[{"l":"/zxdb/sinclair/entries/0025528/0025528-load-1.scr","y":"Loading screen","s":6912},{"l":"/zxdb/sinclair/entries/0025528/0025528-run-1.scr","y":"Running screen","s":6912},{"l":"/zxdb/sinclair/entries/0025528/HadriansWall(Side-1).tzx.zip","y":"Tape image","s":19839},{"l":"/zxdb/sinclair/entries/0025528/HadriansWall(Side-2).tzx.zip","y":"Tape image","s":22456},{"l":"/zxdb/sinclair/entries/0025528/HadriansWall.jpg","y":"Inlay - Front","s":216145}]},{"i":39613,"t":"Haiku Generator","g":"General: Domestic","m":"ZX-Spectrum 48K","f":[{"l":"/zxdb/sinclair/entries/0039613/HaikuGenerator.tzx.zip","y":"Tape image","s":2980},{"l":"/zxdb/sinclair/entries/0039613/HaikuGenerator-RUN-1.scr","y":"Running screen","s":6912}]},{"i":30792,"t":"Hair Fighter Turbo","g":"Arcade Game: Beat-em-up/Solo","m":"ZX-Spectrum 16K","f":[{"l":"/zxdb/sinclair/entries/0030792/HairFighterTurbo.tap.zip","y":"Tape image","s":2090},{"l":"/zxdb/sinclair/entries/0030792/0030792-load-1.scr","y":"Loading screen","s":6912},{"l":"/zxdb/sinclair/entries/0030792/0030792-run-1.scr","y":"Running screen","s":6912}]},{"i":16719,"t":"Hajoverseny","g":"Arcade Game: Action","m":"ZX-Spectrum 128K","f":[{"l":"/pub/sinclair/games/h/Hajoverseny.tzx.zip","y":"Tape image","s":19278},{"l":"/pub/sinclair/games/h/Hajoverseny.z80.zip","y":"Snapshot image","s":18602},{"l":"/pub/sinclair/screens/load/h/scr/Hajoverseny.scr","y":"Loading screen","s":6912},{"l":"/pub/sinclair/screens/in-game/h/Hajoverseny.gif","y":"Running screen","s":6966},{"l":"https://archive.org/download/rzxarchive/hajoverseny.rzx","y":"RZX playback file","s":null}]},{"i":20725,"t":"Hal Ant","g":"Arcade Game: Race 'n' Chase","m":"ZX-Spectrum 48K","f":[{"l":"/pub/sinclair/games/h/HalAnt.tzx.zip","y":"Tape image","s":9759},{"l":"/pub/sinclair/screens/load/h/scr/HalAnt.scr","y":"Loading screen","s":6912},{"l":"/pub/sinclair/screens/in-game/h/HalAnt.gif","y":"Running screen","s":3018}]},{"i":2206,"t":"Halaga","g":"Arcade Game: Shoot-em-up","m":"ZX-Spectrum 48K","f":[{"l":"/pub/sinclair/games/h/Halaga.tzx.zip","y":"Tape image","s":17598},{"l":"/pub/sinclair/games/h/Halaga.tap.zip","y":"Tape image","s":21096},{"l":"/pub/sinclair/screens/load/h/scr/Halaga.scr","y":"Loading screen","s":6912},{"l":"/pub/sinclair/screens/in-game/h/Halaga.gif","y":"Running screen","s":1515},{"l":"/zxdb/sinclair/pokes/h/Halaga (1985)(Interceptor Software).pok","y":"POK pokes file","s":31},{"l":"/zxdb/sinclair/entries/0002206/Halaga(EN).txt","y":"Instructions","s":1328},{"l":"/zxdb/sinclair/entries/0002206/Halaga.jpg","y":"Inlay - Front","s":454877},{"l":"/zxdb/sinclair/entries/0002206/Halaga_2.jpg","y":"Inlay - Front","s":202663},{"l":"/zxdb/sinclair/entries/0002206/Halaga_Media.jpg","y":"Media scan","s":95806}]},{"i":37283,"t":"Halen En Brengen","g":"General: Education","m":"ZX-Spectrum 48K","f":[{"l":"/zxdb/sinclair/entries/0037283/HalenEnBrengen.tzx.zip","y":"Tape image","s":30728},{"l":"/zxdb/sinclair/entries/0037283/HalenEnBrengen_Back.jpg","y":"Inlay - Back","s":315023},{"l":"/zxdb/sinclair/entries/0037283/HalenEnBrengen_Front.jpg","y":"Inlay - Front","s":404682},{"l":"/zxdb/sinclair/entries/0037283/0037283-load-1.scr","y":"Loading screen","s":6912},{"l":"/zxdb/sinclair/entries/0037283/0037283-open-1.scr","y":"Opening screen","s":6912},{"l":"/zxdb/sinclair/entries/0037283/0037283-run-1.scr","y":"Running screen","s":6912},{"l":"/zxdb/sinclair/entries/0037283/HalenEnBrengen_Tape.jpg","y":"Media scan","s":137226}]},{"i":17724,"t":"Hall of Fame","g":"Programming: General","m":"ZX-Spectrum 48K","f":[{"l":"/pub/sinclair/utils/h/HallOfFame.tap.zip","y":"Tape image","s":934},{"l":"/pub/sinclair/screens/in-game/h/HallOfFame.gif","y":"Running screen","s":2396}]},{"i":39763,"t":"Hall of Mirrors","g":"Arcade Game: Action","m":"ZX-Spectrum 48K","f":[{"l":"/zxdb/sinclair/entries/0039763/HallOfMirrors.tap.zip","y":"Tape image","s":2243},{"l":"/zxdb/sinclair/entries/0039763/HallOfMirrors-RUN-1.scr","y":"Running screen","s":6912}]}]