[{"i":27008,"t":"UDG * 8","g":"Utility: Fonts/UDGs","m":"ZX-Spectrum 48K","sc":0,"f":[{"l":"/pub/sinclair/utils/u/UDG8.tzx.zip","y":"Tape image","s":2097},{"l":"/pub/sinclair/screens/in-game/u/UDG8.gif","y":"Running screen","s":2130}]},{"i":32280,"t":"UDG - Creator","g":"Utility: Fonts/UDGs","m":"ZX-Spectrum 48K","sc":0,"f":[{"l":"/zxdb/sinclair/entries/0032280/0032280-load-1.scr","y":"Loading screen","s":6912},{"l":"/zxdb/sinclair/entries/0032280/UDGCreator(Incomplete).tzx.zip","y":"Tape image","s":1513}]},{"i":8914,"t":"UDG Designer","g":"Utility: Fonts/UDGs","m":"ZX-Spectrum 48K","sc":0,"f":[{"l":"/pub/sinclair/utils/u/UDGDesigner.tap.zip","y":"Tape image","s":4056},{"l":"/pub/sinclair/screens/in-game/u/UDGDesigner.gif","y":"Running screen","s":1650}]},{"i":27684,"t":"UDG Generator","g":"Utility: Fonts/UDGs","m":"ZX-Spectrum 16K/48K","sc":0,"f":[{"l":"/pub/sinclair/utils/u/UDGGenerator16.tzx.zip","y":"Tape image","s":1738},{"l":"/pub/sinclair/utils/u/UDGGenerator48.tzx.zip","y":"Tape image","s":1740},{"l":"/pub/sinclair/utils/u/UDGGenerator.dsk.zip","y":"Disk image","s":8443},{"l":"/pub/sinclair/utils/u/UDGGenerator_2.opd.zip","y":"Disk image","s":2493},{"l":"/pub/sinclair/games-info/u/UDGGenerator.jpg","y":"Instructions","s":208220}]},{"i":25987,"t":"UDG Grids","g":"Utility: Fonts/UDGs","m":"ZX-Spectrum 48K","sc":0,"f":[{"l":"/pub/sinclair/utils/u/UDGGrids.tap.zip","y":"Tape image","s":3546},{"l":"/pub/sinclair/screens/in-game/u/UDGGrids.gif","y":"Running screen","s":2239},{"l":"/pub/sinclair/games-info/u/UDGGrids.txt","y":"Instructions","s":401}]},{"i":8915,"t":"UDG Maker","g":"Utility: Fonts/UDGs","m":"ZX-Spectrum 48K","sc":9,"f":[{"l":"/pub/sinclair/utils/u/UDGMaker.z80.zip","y":"Snapshot image","s":6623},{"l":"/pub/sinclair/screens/in-game/u/UDGMaker.gif","y":"Running screen","s":2183}]},{"i":25988,"t":"UDG Plotter","g":"Utility: Fonts/UDGs","m":"ZX-Spectrum 48K","sc":0,"f":[{"l":"/pub/sinclair/utils/u/UDGPlotter.tap.zip","y":"Tape image","s":1295},{"l":"/pub/sinclair/screens/in-game/u/UDGPlotter.gif","y":"Running screen","s":1048},{"l":"/pub/sinclair/games-info/u/UDGPlotter.txt","y":"Instructions","s":1238}]},{"i":8916,"t":"UDG Print","g":"Utility: Fonts/UDGs","m":"ZX-Spectrum 48K","sc":0,"f":[{"l":"/pub/sinclair/utils/u/UDGPrint.z80.zip","y":"Snapshot image","s":3130},{"l":"/pub/sinclair/screens/in-game/u/UDGPrint.gif","y":"Running screen","s":3860}]},{"i":25989,"t":"UDG Search and Replace","g":"Utility: Fonts/UDGs","m":"ZX-Spectrum 16K","sc":0,"f":[{"l":"/pub/sinclair/utils/u/UDGSearchAndReplace.tzx.zip","y":"Tape image","s":528},{"l":"/pub/sinclair/games-info/u/UDGSearchAndReplace.txt","y":"Instructions","s":658}]},{"i":8917,"t":"UDG's Machine","g":"Utility: Fonts/UDGs","m":"ZX-Spectrum 48K","sc":8,"f":[{"l":"/pub/sinclair/utils/u/UDGsMachine.tap.zip","y":"Tape image","s":5648},{"l":"/pub/sinclair/screens/in-game/u/UDGsMachine.gif","y":"Running screen","s":2780}]},{"i":43630,"t":"UDG+","g":"Utility: Graphics","m":"ZX-Spectrum 48K","sc":0,"f":[{"l":"/zxdb/sinclair/entries/0043630/UDG.tzx.zip","y":"Tape image","s":968},{"l":"/zxdb/sinclair/entries/0043630/UDG-RUN-1.scr","y":"Running screen","s":6912}]},{"i":16876,"t":"USP-232D","g":"Utility: I/O Handling","m":"ZX-Spectrum 48K","sc":0,"f":[{"l":"/pub/sinclair/utils/u/USP-232D.tzx.zip","y":"Tape image","s":3155},{"l":"/pub/sinclair/screens/in-game/u/USP-232D.gif","y":"Running screen","s":2079},{"l":"/pub/sinclair/games-inlays/u/USP-232D.jpg","y":"Inlay - Front","s":55418}]},{"i":32294,"t":"UTZ FZX","g":"Utility: Fonts/UDGs","m":"ZX-Spectrum 48K","sc":0,"f":[{"l":"/zxdb/sinclair/entries/0032294/UTZ_FZX.tap.zip","y":"Tape image","s":12001},{"l":"/zxdb/sinclair/entries/0032294/UTZ_FZX_Fonts.zip","y":"Fonts","s":14302}]},{"i":26406,"t":"Ugh!","g":"Utility: Sound/Speech","m":"ZX-Spectrum 48K","sc":0,"f":[{"l":"/pub/sinclair/utils/u/Ugh.tzx.zip","y":"Tape image","s":11615},{"l":"/zxdb/sinclair/entries/0026406/Ugh.scr","y":"Loading screen","s":6912},{"l":"/zxdb/sinclair/entries/0026406/Ugh.gif","y":"Running screen","s":1045}]},{"i":8918,"t":"Ultifile","g":"Utility: Copy/Backup","m":"ZX-Spectrum 48K","sc":0,"f":[{"l":"/pub/sinclair/utils/u/UltifileV3.0.tap.zip","y":"Tape image","s":9032},{"l":"/pub/sinclair/utils/u/UltifileV4.0.tap.zip","y":"Tape image","s":6103},{"l":"/pub/sinclair/screens/load/u/scr/UltifileV4.0.scr","y":"Loading screen","s":6912},{"l":"/pub/sinclair/screens/in-game/u/UltifileV3.0.gif","y":"Running screen","s":2078}]},{"i":31099,"t":"Ultimate Last Minute Sent In Simulator","g":"Utility: Game Creator","m":"ZX-Spectrum 16K","sc":0,"f":[{"l":"/zxdb/sinclair/entries/0031099/UltimateLastMinuteSentInSimulator.tap.zip","y":"Tape image","s":1417},{"l":"/zxdb/sinclair/entries/0031099/0031099-open-1.scr","y":"Opening screen","s":6912},{"l":"/zxdb/sinclair/entries/0031099/0031099-run-1.scr","y":"Running screen","s":6912}]},{"i":8924,"t":"UltraSet","g":"Utility: Fonts/UDGs","m":"ZX-Spectrum 48K","sc":0,"f":[{"l":"/pub/sinclair/utils/u/UltraSet.z80.zip","y":"Snapshot image","s":17654},{"l":"/pub/sinclair/screens/in-game/u/UltraSet.gif","y":"Running screen","s":3620}]},{"i":8920,"t":"Ultracopy","g":"Utility: Copy/Backup","m":"ZX-Spectrum 48K","sc":0,"f":[{"l":"/pub/sinclair/utils/u/Ultracopy.tap.zip","y":"Tape image","s":1345},{"l":"/pub/sinclair/screens/in-game/u/Ultracopy.gif","y":"Running screen","s":1227}]},{"i":8921,"t":"Ultrafile","g":"Utility: Copy/Backup","m":"ZX-Spectrum 48K","sc":0,"f":[{"l":"/pub/sinclair/utils/u/UltrafileV6.tap.zip","y":"Tape image","s":1296},{"l":"/pub/sinclair/utils/u/UltrafileV7.tap.zip","y":"Tape image","s":1478},{"l":"/pub/sinclair/utils/u/UltrafileV8.4.tap.zip","y":"Tape image","s":1786},{"l":"/pub/sinclair/screens/in-game/u/Ultrafile.gif","y":"Running screen","s":1338}]},{"i":27009,"t":"Ultralist","g":"Utility: Print","m":"ZX-Spectrum 48K","sc":0,"f":[{"l":"/zxdb/sinclair/entries/0027009/Ultralist.tap.zip","y":"Tape image","s":4242},{"l":"/zxdb/sinclair/entries/0027009/Ultralist_SourceCode.zip","y":"Source code","s":1429},{"l":"/zxdb/sinclair/entries/0027009/0027009-run-1.scr","y":"Running screen","s":6912}]},{"i":11148,"t":"Unifile","g":"Utility: Media Admin","m":"ZX-Spectrum 48K","sc":0,"f":[{"l":"/pub/sinclair/utils/u/Unifile.tzx.zip","y":"Tape image","s":8124},{"l":"/pub/sinclair/screens/load/u/scr/Unifile.scr","y":"Loading screen","s":6912},{"l":"/pub/sinclair/screens/in-game/u/Unifile.gif","y":"Running screen","s":1850},{"l":"/pub/sinclair/games-info/u/Unifile.pdf","y":"Instructions","s":16909},{"l":"/pub/sinclair/games-inlays/u/Unifile.jpg","y":"Inlay - Front","s":43712}]},{"i":24576,"t":"Unitati de Masura Sistem Anglo-American","g":"Utility: undetermined","m":"ZX-Spectrum 48K","sc":0,"f":[{"l":"/pub/sinclair/utils/u/UnitatiDeMasuraSistemAnglo-American.z80.zip","y":"Snapshot image","s":4706},{"l":"/pub/sinclair/screens/in-game/u/UnitatiDeMasuraSistemAnglo-American.gif","y":"Running screen","s":1852}]},{"i":8926,"t":"Universalschrift","g":"Utility: Fonts/UDGs","m":"ZX-Spectrum 48K","sc":0,"f":[{"l":"/pub/sinclair/utils/u/Universalschrift.z80.zip","y":"Snapshot image","s":8050},{"l":"/pub/sinclair/screens/in-game/u/Universalschrift.gif","y":"Running screen","s":861}]},{"i":38065,"t":"Universo","g":"Utility: Astronomy","m":"ZX-Spectrum 48K","sc":0,"f":[{"l":"/zxdb/sinclair/entries/0038065/Universo.tap.zip","y":"Tape image","s":5765},{"l":"/zxdb/sinclair/entries/0038065/0038065-run-1.scr","y":"Running screen","s":6912}]},{"i":38779,"t":"Uranos","g":"Utility: Prediction","m":"ZX-Spectrum 48K","sc":0,"f":[{"l":"/zxdb/sinclair/entries/0038779/Uranos.tzx.zip","y":"Tape image","s":10771},{"l":"/zxdb/sinclair/entries/0038779/0038779-open-1.scr","y":"Opening screen","s":6912},{"l":"/zxdb/sinclair/entries/0038779/0038779-run-1.scr","y":"Running screen","s":6912}]},{"i":8929,"t":"User Defined Graphics","g":"Utility: Fonts/UDGs","m":"ZX-Spectrum 48K","sc":0,"f":[{"l":"/pub/sinclair/utils/u/UserDefinedGraphics.tzx.zip","y":"Tape image","s":3825},{"l":"/pub/sinclair/utils/u/UserDefinedGraphics.tap.zip","y":"Tape image","s":3746},{"l":"/pub/sinclair/screens/in-game/u/UserDefinedGraphics.gif","y":"Running screen","s":5961}]},{"i":17345,"t":"User Graphic Tablet","g":"Utility: Fonts/UDGs","m":"ZX-Spectrum 16K","sc":0,"f":[{"l":"/pub/sinclair/utils/u/UserGraphicTablet.tap.zip","y":"Tape image","s":2404},{"l":"/pub/sinclair/screens/in-game/u/UserGraphicTablet.gif","y":"Running screen","s":2775},{"l":"/zxdb/sinclair/entries/0017345/UserGraphicTablet(PhippsAssociates).tzx.zip","y":"Tape image","s":2316}]},{"i":27522,"t":"Usr0x01","g":"Utility: I/O Handling","m":"ZX-Spectrum 128K","sc":0,"f":[{"l":"/pub/sinclair/utils/u/Usr0x01.tap.zip","y":"Tape image","s":185},{"l":"/pub/sinclair/games-extras/Usr0x01_SourceCode.zip","y":"Source code","s":1653}]},{"i":13417,"t":"Utility Draw","g":"Utility: Graphics","m":"ZX-Spectrum 16K","sc":0,"f":[{"l":"/pub/sinclair/utils/u/UtilityDraw.tap.zip","y":"Tape image","s":949},{"l":"/pub/sinclair/screens/in-game/u/UtilityDraw.gif","y":"Running screen","s":1932}]},{"i":8932,"t":"Utility1","g":"Utility: Fonts/UDGs","m":"ZX-Spectrum 16K","sc":0,"f":[{"l":"/pub/sinclair/utils/u/Utility1V1.2.tap.zip","y":"Tape image","s":10087},{"l":"/pub/sinclair/screens/load/u/scr/Utility1V1.2.scr","y":"Loading screen","s":6912},{"l":"/pub/sinclair/screens/in-game/u/Utility1V1.2.gif","y":"Running screen","s":1406},{"l":"/pub/sinclair/games-info/u/Utility1V1.2.txt","y":"Instructions","s":2733}]}]